ainodes_backend/__init__.py
ainodes_backend/cldm.py
ainodes_backend/controlnet_loader.py
ainodes_backend/k_sampler.py
ainodes_backend/lora_loader.py
ainodes_backend/model_loader.py
ainodes_backend/poormans_wget.py
ainodes_backend/samplers.py
ainodes_backend/singleton.py
ainodes_backend/sound_recorder.py
ainodes_backend/torch_gc.py
ainodes_backend/cnet_preprocessors/__init__.py
ainodes_backend/cnet_preprocessors/hed.py
ainodes_backend/cnet_preprocessors/midas/__init__.py
ainodes_backend/cnet_preprocessors/midas/api.py
ainodes_backend/cnet_preprocessors/midas/utils.py
ainodes_backend/cnet_preprocessors/midas/midas/__init__.py
ainodes_backend/cnet_preprocessors/midas/midas/base_model.py
ainodes_backend/cnet_preprocessors/midas/midas/blocks.py
ainodes_backend/cnet_preprocessors/midas/midas/dpt_depth.py
ainodes_backend/cnet_preprocessors/midas/midas/midas_net.py
ainodes_backend/cnet_preprocessors/midas/midas/midas_net_custom.py
ainodes_backend/cnet_preprocessors/midas/midas/transforms.py
ainodes_backend/cnet_preprocessors/midas/midas/vit.py
ainodes_backend/cnet_preprocessors/mlsd/__init__.py
ainodes_backend/cnet_preprocessors/mlsd/utils.py
ainodes_backend/cnet_preprocessors/openpose/__init__.py
ainodes_backend/cnet_preprocessors/openpose/body.py
ainodes_backend/cnet_preprocessors/openpose/hand.py
ainodes_backend/cnet_preprocessors/openpose/model.py
ainodes_backend/cnet_preprocessors/openpose/util.py
ainodes_backend/inpaint/__init__.py
ainodes_backend/inpaint/ddim_sampler.py
ainodes_backend/inpaint/generator.py
ainodes_backend/inpaint/inpaint_sampling_utils.py
ainodes_backend/matte/__init__.py
ainodes_backend/matte/decoder.py
ainodes_backend/matte/deep_guided_filter.py
ainodes_backend/matte/fast_guided_filter.py
ainodes_backend/matte/lraspp.py
ainodes_backend/matte/matte.py
ainodes_backend/matte/mobilenetv3.py
ainodes_backend/matte/model.py
ainodes_backend/matte/resnet.py
ainodes_backend/node_engine/__init__.py
ainodes_backend/node_engine/node_content_widget.py
ainodes_engine-0.1.1.dist-info/LICENSE
ainodes_engine-0.1.1.dist-info/METADATA
ainodes_engine-0.1.1.dist-info/WHEEL
ainodes_engine-0.1.1.dist-info/entry_points.txt
ainodes_engine-0.1.1.dist-info/top_level.txt
ainodes_engine-0.1.1.dist-info/RECORD
