Metadata-Version: 2.1
Name: ainodes-engine
Version: 0.1.1
Author: deforum
Author-email: miklos.mnagy@gmail.com
License-File: LICENSE
Requires-Dist: virtualenv
